ccc/__init__.py
ccc/agent.py
ccc/cli.py
ccc/config.py
ccc_cli_helper-0.2.2.dist-info/licenses/LICENSE
ccc_cli_helper-0.2.2.dist-info/METADATA
ccc_cli_helper-0.2.2.dist-info/WHEEL
ccc_cli_helper-0.2.2.dist-info/entry_points.txt
ccc_cli_helper-0.2.2.dist-info/top_level.txt
ccc_cli_helper-0.2.2.dist-info/RECORD
